multicluster_mcp_server/__init__.py
multicluster_mcp_server/__main__.py
multicluster_mcp_server/core/__init__.py
multicluster_mcp_server/core/mcp_instance.py
multicluster_mcp_server/tools/__init__.py
multicluster_mcp_server/tools/cluster.py
multicluster_mcp_server/tools/connect.py
multicluster_mcp_server/tools/kubectl.py
multicluster_mcp_server/tools/prometheus.py
multicluster_mcp_server/utils/__init__.py
multicluster_mcp_server/utils/logging_config.py
multicluster_mcp_server/utils/prom_connect.py
multicluster_mcp_server-0.1.6.dist-info/METADATA
multicluster_mcp_server-0.1.6.dist-info/WHEEL
multicluster_mcp_server-0.1.6.dist-info/entry_points.txt
multicluster_mcp_server-0.1.6.dist-info/RECORD
