Metadata-Version: 2.3
Name: multicluster-mcp-server
Version: 0.1.6
Summary: The gateway for GenAI systems to interact with multiple Kubernetes clusters through the MCP
License: MIT
Keywords: MCP,python,Kubernetes,Multi-Cluster,open-cluster-management
Author: myan
Author-email: myan@redhat.com
Requires-Python: >=3.11
Classifier: License :: OSI Approved :: MIT License
Classifier: Programming Language :: Python :: 3
Classifier: Programming Language :: Python :: 3.11
Classifier: Programming Language :: Python :: 3.12
Classifier: Programming Language :: Python :: 3.13
Requires-Dist: kubernetes (>=32.0.1)
Requires-Dist: mcp[cli] (>=1.8.0)
Requires-Dist: prometheus-api-client (>=0.6.0,<0.7.0)
Project-URL: Repository, https://github.com/yanmxa/multicluster-mcp-server
